MANIFEST.in
README.md
requirements.txt
setup.py
src/fastdataing/__init__.py
src/fastdataing/fastdataing.py
src/fastdataing/figure.py
src/fastdataing/files.py
src/fastdataing/formula2mass.py
src/fastdataing/paper.py
src/fastdataing/print_line.py
src/fastdataing.egg-info/PKG-INFO
src/fastdataing.egg-info/SOURCES.txt
src/fastdataing.egg-info/dependency_links.txt
src/fastdataing.egg-info/requires.txt
src/fastdataing.egg-info/top_level.txt